pg_docker/__init__.py
pg_docker/_core.py
pg_docker/_plugin.py
pg_docker/py.typed
pg_docker-0.11.0.dist-info/WHEEL
pg_docker-0.11.0.dist-info/entry_points.txt
pg_docker-0.11.0.dist-info/METADATA
pg_docker-0.11.0.dist-info/RECORD
